threador/__init__.py
threador/thread_utils.py
pythreador-0.1.2.dist-info/entry_points.txt
pythreador-0.1.2.dist-info/WHEEL
pythreador-0.1.2.dist-info/METADATA
pythreador-0.1.2.dist-info/RECORD
