Metadata-Version: 2.1
Name: pythreador
Version: 0.1.2
Summary: threador is a tool for formatting tweet threads
Requires-Python: >=3.7
